README
setup.py
spassw/__init__.py
spassw/cmdline.py
spassw/spassw.py
spassw.egg-info/PKG-INFO
spassw.egg-info/SOURCES.txt
spassw.egg-info/dependency_links.txt
spassw.egg-info/entry_points.txt
spassw.egg-info/not-zip-safe
spassw.egg-info/top_level.txt