Metadata-Version: 1.1
Name: spassw
Version: 0.1
Summary: The simple password generator
Home-page: http://github.com/iokacha/py-spassw
Author: OKACHA Ilias
Author-email: i.okacha@gmail.com
License: MIT
Keywords: Password generation simple secure no+dependency
Platform: UNKNOWN
Classifier: Development Status :: 3 - Alpha
Classifier: License :: OSI Approved :: MIT License
Classifier: Programming Language :: Python :: 3.6
Classifier: Environment :: Console
Classifier: Topic :: System :: Systems Administration
